distributions_mini/Binomialdistribution.py
distributions_mini/Gaussiandistribution.py
distributions_mini/Generaldistribution.py
distributions_mini/__init__.py
distributions_mini-0.1.dist-info/DESCRIPTION.rst
distributions_mini-0.1.dist-info/METADATA
distributions_mini-0.1.dist-info/RECORD
distributions_mini-0.1.dist-info/WHEEL
distributions_mini-0.1.dist-info/metadata.json
distributions_mini-0.1.dist-info/top_level.txt
