Metadata-Version: 2.0
Name: distributions-mini
Version: 0.1
Summary: Gaussian distributions
Home-page: UNKNOWN
Author: Idris Aminat
Author-email: UNKNOWN
License: UNKNOWN
Platform: UNKNOWN
